sexSorter/__main__.py
sexSorter/sorter.py
sex_sorter-1.0.0.dist-info/METADATA
sex_sorter-1.0.0.dist-info/WHEEL
sex_sorter-1.0.0.dist-info/licenses/LICENSE
sex_sorter-1.0.0.dist-info/RECORD
