Metadata-Version: 2.3
Name: sex-sorter
Version: 1.0.0
Summary: Sorts character by sex
Project-URL: Homepage, https://git.fearvel.de/tools/python/sex-sorter
Author-email: Andreas Schreiner <fearvel@proton.me>
License-File: LICENSE
Classifier: License :: OSI Approved :: MIT License
Requires-Dist: anime-character-sex-analyzer
